holo/__init__.py
holo/holo.py
holo-0.1.3.dist-info/LICENSE
holo-0.1.3.dist-info/WHEEL
holo-0.1.3.dist-info/METADATA
holo-0.1.3.dist-info/RECORD
