Metadata-Version: 2.1
Name: holo
Version: 0.1.3
Summary: Holo is a library provides overload like cpp
Home-page: https://github.com/Na0ture/holo
Keywords: overload
Author: lvzhi
Author-email: 279094354@qq.com
Requires-Python: >=3.7,<4.0
Classifier: Development Status :: 5 - Production/Stable
Classifier: Programming Language :: Python :: 3
Classifier: Programming Language :: Python :: 3.7
Classifier: Programming Language :: Python :: 3.8
Classifier: Programming Language :: Python :: 3.9
Classifier: Topic :: Software Development :: Libraries :: Python Modules
Project-URL: Repository, https://github.com/Na0ture/holo
